djsuperadmin/__init__.py
djsuperadmin/apps.py
djsuperadmin/mixins.py
djsuperadmin/settings.py
djsuperadmin/dist/djsuperadmin.bundle.js
djsuperadmin/templatetags/__init__.py
djsuperadmin/templatetags/djsuperadmintag.py
djsuperadmin-0.11.3.dist-info/LICENSE
djsuperadmin-0.11.3.dist-info/METADATA
djsuperadmin-0.11.3.dist-info/WHEEL
djsuperadmin-0.11.3.dist-info/top_level.txt
djsuperadmin-0.11.3.dist-info/RECORD
