Metadata-Version: 2.1
Name: djsuperadmin
Version: 0.11.3
Summary: Edit contents directly on your page with Django
Home-page: https://github.com/lotrekagency/djsuperadmin
Author: Lotrèk
Author-email: dimmitutto@lotrek.it
License: MIT
Keywords: cms,django,api cms
Platform: UNKNOWN
Classifier: Environment :: Web Environment
Classifier: Framework :: Django
Classifier: Intended Audience :: Developers
Classifier: Programming Language :: Python
Classifier: Programming Language :: Python :: 3
Requires-Python: >=3.0.*
License-File: LICENSE
